pysilk/utils.py
pysilk/coder.pypy38-pp73-x86_64-linux-gnu.so
pysilk/pysilk.py
pysilk/__init__.py
pysilk/__main__.py
pysilk/wav.py
pysilk_mod-1.6.4.dist-info/top_level.txt
pysilk_mod-1.6.4.dist-info/RECORD
pysilk_mod-1.6.4.dist-info/LICENSE
pysilk_mod-1.6.4.dist-info/zip-safe
pysilk_mod-1.6.4.dist-info/METADATA
pysilk_mod-1.6.4.dist-info/WHEEL
