Metadata-Version: 2.1
Name: pysilk-mod
Version: 1.6.4
Summary: Python silk decode/encoder
Home-page: https://github.com/DCZYewen/Python-Silk-Module
Author: DCZYewen
Author-email: contact@basicws.net
Maintainer: wyapx
Maintainer-email: admin@nullcat.cn
License: see LICENSE
Project-URL: Source Code, https://github.com/DCZYewen/Python-Silk-Module
Project-URL: Issue tracker, https://github.com/DCZYewen/Python-Silk-Module/issues
Requires: pybind11
Requires: setuptools
Requires-Python: >=3.8
License-File: LICENSE
